tests/__init__.py
tests/test_auth.py
tests/test_auth_object_re.py
tests/test_download.py
tests/test_search.py
univk_audio/__init__.py
univk_audio/async_auth.py
univk_audio/async_client.py
univk_audio/auth_exceptions.py
univk_audio/client_exceptions.py
univk_audio/request_data.py
univk_audio-1.0.3.dist-info/LICENSE
univk_audio-1.0.3.dist-info/METADATA
univk_audio-1.0.3.dist-info/WHEEL
univk_audio-1.0.3.dist-info/top_level.txt
univk_audio-1.0.3.dist-info/RECORD
