Metadata-Version: 2.1
Name: univk-audio
Version: 1.0.3
Summary: An easy-to-use library that allows you to search and download audio from VK, bypassing the restriction on obtaining a token to use the VK audio API.
Home-page: https://github.com/Exponefrv1/univk_audio
Author: Unik
Project-URL: Homepage, https://github.com/Exponefrv1/univk_audio
Project-URL: Issues, https://github.com/Exponefrv1/univk_audio/issues
Project-URL: Author, https://t.me/AnemoneSong
Keywords: vk audio music songs search download free univk vk_audio
Classifier: Programming Language :: Python :: 3
Classifier: License :: OSI Approved :: MIT License
Classifier: Operating System :: OS Independent
Requires-Python: >=3.7
License-File: LICENSE
Requires-Dist: aiofiles
Requires-Dist: aiohttp
Requires-Dist: beautifulsoup4
Requires-Dist: httpx
Requires-Dist: lxml
